aib_logging/__init__.py
aib_logging/logger.py
aib_logging-1.0.9.dist-info/LICENSE.txt
aib_logging-1.0.9.dist-info/METADATA
aib_logging-1.0.9.dist-info/WHEEL
aib_logging-1.0.9.dist-info/top_level.txt
aib_logging-1.0.9.dist-info/RECORD
