Metadata-Version: 2.1
Name: aib-logging
Version: 1.0.9
Summary: A small example package
Author-email: akib Shaikh <shaikhakib.k@gmail.com>, karim ramzy <karimatefhenry@gmail.com>, muhammad badawy <muhammad.i.badawy@gmail.com>
Project-URL: Homepage, https://github.com/pypa/sampleproject
Project-URL: Bug Tracker, https://github.com/pypa/sampleproject/issues
Classifier: Programming Language :: Python :: 3
Classifier: License :: OSI Approved :: MIT License
Classifier: Operating System :: OS Independent
Requires-Python: >=3.7
License-File: LICENSE.txt
Requires-Dist: google-cloud-logging (==3.2.5)
